data_api_mapper/__init__.py
data_api_mapper/appsync.py
data_api_mapper/converters.py
data_api_mapper/data_api.py
data_api_mapper/utils.py
data_api_mapper-1.2.4.dist-info/LICENSE
data_api_mapper-1.2.4.dist-info/METADATA
data_api_mapper-1.2.4.dist-info/WHEEL
data_api_mapper-1.2.4.dist-info/top_level.txt
data_api_mapper-1.2.4.dist-info/RECORD
