Metadata-Version: 2.1
Name: data-api-mapper
Version: 1.2.4
Summary: A very simplistic AWS Aurora Serverless Data API mapper
Home-page: https://github.com/get-carefull/data-api-mapper
Author: Flavio Oliveri
Author-email: flavio.oliveri@gmail.com
License: UNKNOWN
Platform: UNKNOWN
Classifier: Intended Audience :: Developers
Classifier: License :: OSI Approved :: MIT License
Classifier: Programming Language :: Python :: 3.8
